[
  {"id": 1, "name": "А. Петров", "rating": 5, "text": "Быстро, качественно, всё чётко.", "date": "12.04"},
  {"id": 2, "name": "Е. Соколова", "rating": 5, "text": "Очень приятный сервис. Номер получила за два дня, как и обещали.", "date": "08.04"},
  {"id": 3, "name": "И. Козлов", "rating": 5, "text": "Рекомендую! Честные цены, без скрытых комиссий.", "date": "05.04"},
  {"id": 4, "name": "М. Новикова", "rating": 5, "text": "Долго искала красивый номер — здесь нашла идеальный вариант.", "date": "01.04"},
  {"id": 5, "name": "Д. Волков", "rating": 5, "text": "Всё прозрачно, документы оформили быстро. Спасибо!", "date": "28.03"},
  {"id": 6, "name": "О. Морозова", "rating": 5, "text": "Первый раз покупала номер — консультант всё объяснил по шагам.", "date": "24.03"},
  {"id": 7, "name": "С. Лебедев", "rating": 5, "text": "Качество на высоте. Буду рекомендовать знакомым.", "date": "20.03"},
  {"id": 8, "name": "Н. Кузнецова", "rating": 5, "text": "Удобно, быстро, приятные цены. Очень довольна.", "date": "15.03"},
  {"id": 9, "name": "В. Попов", "rating": 5, "text": "Профессиональный подход. Всё как надо.", "date": "10.03"},
  {"id": 10, "name": "Т. Федорова", "rating": 5, "text": "Отличный сервис! Номер мечты наконец у меня.", "date": "05.03"}
]
